open_excel
setup.py
open_excel/__init__.py
open_excel/open_excel.py
open_excel/search_excel.py
open_excel.egg-info/PKG-INFO
open_excel.egg-info/SOURCES.txt
open_excel.egg-info/dependency_links.txt
open_excel.egg-info/requires.txt
open_excel.egg-info/top_level.txt