Metadata-Version: 1.2
Name: open-excel
Version: 0.101a0
Summary: Ansible Modules to Search/Read an Excel file and register its content into an ansible list of dict
Home-page: https://github.com/mohameosam/open_excel
Author: Mohamed Abouahmed, Kovarus Inc., San Ramon, CA <mabouahmed@kovarus.com>
Author-email: mohamedosam@gmail.com
License: GPL v3
Keywords: excel,search,spreadsheet
Platform: UNKNOWN
Requires-Python: >=2.7
